iprecon/__init__.py
iprecon/__main__.py
iprecon/client.py
iprecon/ip.py
iprecon/log.py
iprecon/network.py
iprecon/output.py
iprecon/utils.py
iprecon-1.0.0.dist-info/METADATA
iprecon-1.0.0.dist-info/WHEEL
iprecon-1.0.0.dist-info/entry_points.txt
iprecon-1.0.0.dist-info/top_level.txt
iprecon-1.0.0.dist-info/RECORD
