Metadata-Version: 2.1
Name: iprecon
Version: 1.0.0
Summary: CLI tool that retrieves WHOIS data for IP addresses
Author-email: Dominic Breuker <admin@dominicbreuker.com>
Project-URL: Homepage, https://github.com/dominicbreuker/iprecon
Keywords: ip,whois,recon,security,bug-bounty
Classifier: License :: OSI Approved :: BSD License
Classifier: Programming Language :: Python
Classifier: Programming Language :: Python :: 3
Requires-Python: >=3.10
Requires-Dist: ipwhois (~=1.2.0)
Provides-Extra: dev
Requires-Dist: black ; extra == 'dev'
Requires-Dist: bumpver ; extra == 'dev'
Requires-Dist: pytest ; extra == 'dev'
Requires-Dist: build ; extra == 'dev'
Requires-Dist: twine ; extra == 'dev'
